MANIFEST.in
README.txt
setup.py
collective/__init__.py
collective.portlet.wordpress.egg-info/PKG-INFO
collective.portlet.wordpress.egg-info/SOURCES.txt
collective.portlet.wordpress.egg-info/dependency_links.txt
collective.portlet.wordpress.egg-info/entry_points.txt
collective.portlet.wordpress.egg-info/namespace_packages.txt
collective.portlet.wordpress.egg-info/not-zip-safe
collective.portlet.wordpress.egg-info/requires.txt
collective.portlet.wordpress.egg-info/top_level.txt
collective/portlet/__init__.py
collective/portlet/wordpress/__init__.py
collective/portlet/wordpress/configure.zcml
collective/portlet/wordpress/wordpress.pt
collective/portlet/wordpress/wordpress.py
collective/portlet/wordpress/locales/collective.portlet.wordpress.pot
collective/portlet/wordpress/profiles/default/metadata.xml
collective/portlet/wordpress/profiles/default/portlets.xml
collective/portlet/wordpress/tests/__init__.py
collective/portlet/wordpress/tests/base.py
collective/portlet/wordpress/tests/dummy_server.py
collective/portlet/wordpress/tests/test_wordpressblogportlet.py
collective/portlet/wordpress/tests/data/not_xml?feed=rss2
collective/portlet/wordpress/tests/data/test?feed=rss2
docs/HISTORY.txt
docs/INSTALL.txt
docs/LICENSE.GPL
docs/LICENSE.txt