Metadata-Version: 1.0
Name: collective.portlet.wordpress
Version: 1.0
Summary: This package provides portlet that lists blog posts from your wordpress blog.
Home-page: https://svn.plone.org/svn/collective/collective.portlet.wordpress
Author: Vitaliy Podoba
Author-email: vitaliy@martinschoel.com
License: GPL
Keywords: portlet wordpress
Platform: UNKNOWN
Classifier: Framework :: Plone
Classifier: Programming Language :: Python
